smol_k8s_lab/__init__.py
smol_k8s_lab/audio/audio-en.tar.gz
smol_k8s_lab/bitwarden/bw_cli.py
smol_k8s_lab/bitwarden/tui/bitwarden.css
smol_k8s_lab/bitwarden/tui/bitwarden_app.py
smol_k8s_lab/bitwarden/tui/bitwarden_credentials_modal_screen.py
smol_k8s_lab/bitwarden/tui/bitwarden_existing_item.tcss
smol_k8s_lab/bitwarden/tui/bitwarden_existing_item_app.py
smol_k8s_lab/config/audio/en.yml
smol_k8s_lab/config/audio/nl.yml
smol_k8s_lab/config/default_config.yaml
smol_k8s_lab/config/keycloak_config.json
smol_k8s_lab/config/kind/kind-config-cilium.yaml
smol_k8s_lab/config/kind/kind_cluster_config.yaml
smol_k8s_lab/config/smol-k8s-lab.appdata.xml
smol_k8s_lab/constants.py
smol_k8s_lab/env_config.py
smol_k8s_lab/k8s_apps/__init__.py
smol_k8s_lab/k8s_apps/argocd.py
smol_k8s_lab/k8s_apps/identity_provider/__init__.py
smol_k8s_lab/k8s_apps/identity_provider/keycloak.py
smol_k8s_lab/k8s_apps/identity_provider/vouch.py
smol_k8s_lab/k8s_apps/identity_provider/zitadel.py
smol_k8s_lab/k8s_apps/identity_provider/zitadel_api.py
smol_k8s_lab/k8s_apps/ingress/cert_manager.py
smol_k8s_lab/k8s_apps/ingress/ingress_nginx_controller.py
smol_k8s_lab/k8s_apps/initial_special.py
smol_k8s_lab/k8s_apps/monitoring/prometheus_stack.py
smol_k8s_lab/k8s_apps/networking/__init__.py
smol_k8s_lab/k8s_apps/networking/cilium.py
smol_k8s_lab/k8s_apps/networking/metallb.py
smol_k8s_lab/k8s_apps/networking/netmaker.py
smol_k8s_lab/k8s_apps/operators/__init__.py
smol_k8s_lab/k8s_apps/operators/minio.py
smol_k8s_lab/k8s_apps/operators/openbao.py
smol_k8s_lab/k8s_apps/operators/postgres_operators.py
smol_k8s_lab/k8s_apps/operators/seaweedfs.py
smol_k8s_lab/k8s_apps/secrets_management/__init__.py
smol_k8s_lab/k8s_apps/secrets_management/external_secrets_operator.py
smol_k8s_lab/k8s_apps/secrets_management/infisical.py
smol_k8s_lab/k8s_apps/secrets_management/vault.py
smol_k8s_lab/k8s_apps/social/collabora_online.py
smol_k8s_lab/k8s_apps/social/forgejo.py
smol_k8s_lab/k8s_apps/social/ghost.py
smol_k8s_lab-6.4.8.dist-info/LICENSE
smol_k8s_lab-6.4.8.dist-info/METADATA
smol_k8s_lab-6.4.8.dist-info/WHEEL
smol_k8s_lab-6.4.8.dist-info/entry_points.txt
smol_k8s_lab-6.4.8.dist-info/RECORD
