Metadata-Version: 2.3
Name: smol_k8s_lab
Version: 6.4.8
Summary: CLI and TUI to quickly install slimmer Kubernetes distros and then manage apps declaratively using Argo CD
License: AGPL-3.0-or-later
Keywords: kubernetes,homelab,kind,k3s,k8s
Author: Jesse Hitch
Author-email: jessebot@linux.com
Requires-Python: >=3.11,<3.13
Classifier: Development Status :: 4 - Beta
Classifier: Intended Audience :: End Users/Desktop
Classifier: License :: OSI Approved :: GNU Affero General Public License v3 or later (AGPLv3+)
Classifier: Operating System :: MacOS :: MacOS X
Classifier: Operating System :: POSIX :: Linux
Classifier: Programming Language :: Python :: 3
Classifier: Programming Language :: Python :: 3.11
Classifier: Programming Language :: Python :: 3.12
Classifier: Topic :: System :: Installation/Setup
Requires-Dist: bcrypt (>=4.2,<5.0)
Requires-Dist: click (>=8.1,<9.0)
Requires-Dist: cryptography (>=44.0,<45.0)
Requires-Dist: kubernetes (>=31,<32)
Requires-Dist: minio (>=7.2,<8.0)
Requires-Dist: pyfiglet (>=1.0,<2.0)
Requires-Dist: pygame (>=2.5,<3.0)
Requires-Dist: pyjwt (>=2.10,<3.0)
Requires-Dist: python-ulid (>=3.0,<4.0)
Requires-Dist: pyyaml (>=6.0,<7.0)
Requires-Dist: requests (>=2.32,<3.0)
Requires-Dist: rich (>=13.9,<14.0)
Requires-Dist: ruamel-yaml (>=0.18,<0.19)
Requires-Dist: ruamel-yaml-string (>=0.1,<0.2)
Requires-Dist: textual (>=1.0,<2.0)
Requires-Dist: xdg-base-dirs (>=6.0,<7.0)
Project-URL: Bug Tracker, http://github.com/small-hack/smol-k8s-lab/issues
Project-URL: Documentation, https://small-hack.github.io/smol-k8s-lab
Project-URL: Homepage, https://small-hack.github.io/smol-k8s-lab
Project-URL: Repository, http://github.com/small-hack/smol-k8s-lab
